microcrawler/__init__.py
microcrawler/arrivals.py
microcrawler-0.0.2.dist-info/METADATA
microcrawler-0.0.2.dist-info/WHEEL
microcrawler-0.0.2.dist-info/entry_points.txt
microcrawler-0.0.2.dist-info/top_level.txt
microcrawler-0.0.2.dist-info/RECORD
